{
  "name": "fullyfarmablesand:desert_catacombs_medium_room_connect/medium_room",
  "fallback": "minecraft:empty",
  "elements": [
    {
      "weight": 3,
      "element": {
        "location": "fullyfarmablesand:desert_catacombs/medium_rooms/medium_room_1",
        "processors": "fullyfarmablesand:desert_catacombs",
        "projection": "rigid",
        "element_type": "minecraft:single_pool_element"
      }
    },
    {
      "weight": 4,
      "element": {
        "location": "fullyfarmablesand:desert_catacombs/medium_rooms/medium_room_2",
        "processors": "fullyfarmablesand:desert_catacombs",
        "projection": "rigid",
        "element_type": "minecraft:single_pool_element"
      }
    },
    {
      "weight": 4,
      "element": {
        "location": "fullyfarmablesand:desert_catacombs/medium_rooms/medium_room_3",
        "processors": "fullyfarmablesand:desert_catacombs",
        "projection": "rigid",
        "element_type": "minecraft:single_pool_element"
      }
    }
  ]
}