{
  "type": "minecraft:chest",
  "pools": [
    {
      "bonus_rolls": 0.0,
      "entries": [
        {
          "type": "minecraft:item",
          "name": "minecraft:archer_pottery_sherd"
        },
        {
          "type": "minecraft:item",
          "name": "minecraft:brewer_pottery_sherd"
        },
        {
          "type": "minecraft:item",
          "name": "minecraft:skull_pottery_sherd"
        },
        {
          "type": "minecraft:item",
          "name": "minecraft:diamond"
        },
        {
          "type": "minecraft:item",
          "name": "minecraft:tnt"
        },
        {
          "type": "minecraft:item",
          "functions": [
            {
              "add": false,
              "count": {
                "type": "minecraft:uniform",
                "max": 4.0,
                "min": 2.0
              },
              "function": "minecraft:set_count"
            }
          ],
          "name": "minecraft:emerald"
        },
        {
          "type": "minecraft:item",
          "functions": [
            {
              "function": "minecraft:enchant_with_levels",
              "levels": 15.0,
              "treasure": true
            }
          ],
          "name": "minecraft:book"
        }
      ],
      "rolls": 1.0
    }
  ],
  "random_sequence": "fullyfarmablesand:pots/desert_catacombs_rare"
}